README.txt
setup.py
docs/HISTORY.txt
docs/INSTALL.txt
docs/LICENSE.GPL
docs/LICENSE.txt
monet/__init__.py
monet.mapsviewlet.egg-info/PKG-INFO
monet.mapsviewlet.egg-info/SOURCES.txt
monet.mapsviewlet.egg-info/dependency_links.txt
monet.mapsviewlet.egg-info/entry_points.txt
monet.mapsviewlet.egg-info/namespace_packages.txt
monet.mapsviewlet.egg-info/not-zip-safe
monet.mapsviewlet.egg-info/requires.txt
monet.mapsviewlet.egg-info/top_level.txt
monet/mapsviewlet/__init__.py
monet/mapsviewlet/configure.zcml
monet/mapsviewlet/extender.py
monet/mapsviewlet/interfaces.py
monet/mapsviewlet/permissions.py
monet/mapsviewlet/permissions.zcml
monet/mapsviewlet/profiles.zcml
monet/mapsviewlet/setuphandlers.py
monet/mapsviewlet/vocabularies.py
monet/mapsviewlet/Extensions/install.py
monet/mapsviewlet/adapter/__init__.py
monet/mapsviewlet/adapter/configure.zcml
monet/mapsviewlet/adapter/location.py
monet/mapsviewlet/adapter/maps.py
monet/mapsviewlet/browser/__init__.py
monet/mapsviewlet/browser/configure.zcml
monet/mapsviewlet/browser/map.py
monet/mapsviewlet/browser/maps_view.py
monet/mapsviewlet/browser/images/googleearth_icon.gif
monet/mapsviewlet/browser/javascripts/monet_googlemaps.js
monet/mapsviewlet/browser/javascripts/monet_mapswidgetfix.js
monet/mapsviewlet/browser/styles/maps.css
monet/mapsviewlet/locales/i18n.sh
monet/mapsviewlet/locales/monet.mapsviewlet-manual.pot
monet/mapsviewlet/locales/monet.mapsviewlet.pot
monet/mapsviewlet/locales/it/LC_MESSAGES/monet.mapsviewlet.po
monet/mapsviewlet/portlets/__init__.py
monet/mapsviewlet/portlets/configure.zcml
monet/mapsviewlet/portlets/kml.py
monet/mapsviewlet/portlets/kml_controls.pt
monet/mapsviewlet/profiles/default/actions.xml
monet/mapsviewlet/profiles/default/browserlayer.xml
monet/mapsviewlet/profiles/default/cssregistry.xml
monet/mapsviewlet/profiles/default/import_steps.xml
monet/mapsviewlet/profiles/default/jsregistry.xml
monet/mapsviewlet/profiles/default/metadata.xml
monet/mapsviewlet/profiles/default/monet.mapsviewlet_various.txt
monet/mapsviewlet/profiles/default/portlets.xml
monet/mapsviewlet/profiles/default/rolemap.xml
monet/mapsviewlet/profiles/uninstall/actions.xml
monet/mapsviewlet/profiles/uninstall/cssregistry.xml
monet/mapsviewlet/profiles/uninstall/import_steps.xml
monet/mapsviewlet/profiles/uninstall/jsregistry.xml
