Metadata-Version: 1.0
Name: monet.mapsviewlet
Version: 0.6.1
Summary: A viewlet for Plone that show up a Google Maps using the document location field. Also can handle KML files using related contents.
Home-page: http://plone.org/products/monet.mapsviewlet
Author: RedTurtle Technology
Author-email: sviluppoplone@redturtle.it
License: GPL
Keywords: plone monet google maps plonegov kml
Platform: UNKNOWN
Classifier: Framework :: Plone
Classifier: Programming Language :: Python
Classifier: Topic :: Software Development :: Libraries :: Python Modules
Classifier: Development Status :: 4 - Beta
Classifier: Topic :: Scientific/Engineering :: GIS
